OFF-chip Protocols/SPI/SLAVE.v
module spi_slave #(
  parameter CPOL = 0,
  parameter CPHA = 0
)(
  input  wire       sclk,
  input  wire       cs_n,
  input  wire       rst_n,     // ✅ added reset
  input  wire       mosi,
  input  wire [7:0] tx_data,
  output reg        miso,
  output reg [7:0]  rx_data
);

  reg [7:0] tx_shift;
  reg [7:0] rx_shift;
  reg [2:0] bit_cnt;

  wire sample_edge = (CPHA == 0) ?  sclk : ~sclk;
  wire shift_edge  = (CPHA == 0) ? ~sclk :  sclk;

  /* ✅ Reset + Load data at CS falling edge */
  always @(negedge cs_n or negedge rst_n) begin
    if (!rst_n) begin
      bit_cnt  <= 3'd0;
      tx_shift <= 8'd0;
      rx_shift <= 8'd0;
    end else begin
      bit_cnt  <= 3'd7;
      tx_shift <= tx_data;
      rx_shift <= 8'd0;
    end
  end

  /* SPI clocking */
  always @(posedge sclk or negedge sclk or negedge rst_n) begin
    if (!rst_n) begin
      miso <= 1'b0;
    end else if (!cs_n) begin

      /* Shift out */
      if (shift_edge) begin
        miso     <= tx_shift[7];
        tx_shift <= tx_shift << 1;
      end

      /* Shift in */
      if (sample_edge) begin
        rx_shift <= {rx_shift[6:0], mosi};
        bit_cnt  <= bit_cnt - 1;
      end

    end
  end

  /* ✅ Reset + latch RX when CS goes high */
  always @(posedge cs_n or negedge rst_n) begin
    if (!rst_n)
      rx_data <= 8'd0;
    else
      rx_data <= rx_shift;
  end

endmodule

OFF-chip Protocols/SPI/MASTER.v
module spi_master #(
  parameter CPOL = 0,
  parameter CPHA = 0
)(
  input  wire       clk,
  input  wire       rst_n,
  input  wire       start,
  input  wire [7:0] tx_data,
  input  wire       miso,
  output reg        sclk,
  output reg        mosi,
  output reg [7:0]  rx_data,
  output reg        busy
);

  reg [7:0] tx_shift, rx_shift;
  reg [2:0] bit_cnt;
  reg       done_pending;

  wire sample_edge = (CPHA == 0) ?  sclk : ~sclk;
  wire shift_edge  = (CPHA == 0) ? ~sclk :  sclk;

  always @(posedge clk or negedge rst_n) begin
    if (!rst_n) begin
      sclk <= CPOL;
      busy <= 0;
      done_pending <= 0;
      rx_data <= 0;
    end else begin

      if (start && !busy) begin
        busy <= 1;
        bit_cnt <= 3'd7;
        tx_shift <= tx_data;
        rx_shift <= 0;
        sclk <= CPOL;
        done_pending <= 0;
      end

      else if (busy) begin
        sclk <= ~sclk;

        if (shift_edge)
          mosi <= tx_shift[bit_cnt];

        if (sample_edge) begin
          rx_shift[bit_cnt] <= miso;

          if (bit_cnt == 0)
            done_pending <= 1;
          else
            bit_cnt <= bit_cnt - 1;
        end

        if (done_pending && shift_edge) begin
          rx_data <= rx_shift;
          busy <= 0;
          sclk <= CPOL;
          done_pending <= 0;
        end
      end
    end
  end
endmodule

OFF-chip Protocols/SPI/TOP.v
module spi_top #(
  parameter CPOL = 0,
  parameter CPHA = 0
)(
  input  wire       clk,
  input  wire       rst_n,
  input  wire       start,
  input  wire [7:0] master_tx_data,
  input  wire [7:0] slave_tx_data,
  output wire [7:0] master_rx_data,
  output wire [7:0] slave_rx_data,
  output wire       busy
);

  wire sclk;
  wire mosi;
  wire miso;
  wire cs_n;

  assign cs_n = ~busy;   // slave selected while busy

  // -------- MASTER --------
  spi_master #(
    .CPOL(CPOL),
    .CPHA(CPHA)
  ) u_master (
    .clk     (clk),
    .rst_n   (rst_n),
    .start   (start),
    .tx_data (master_tx_data),
    .miso    (miso),
    .sclk    (sclk),
    .mosi    (mosi),
    .rx_data (master_rx_data),
    .busy    (busy)
  );

  // -------- SLAVE --------
  spi_slave #(
    .CPOL(CPOL),
    .CPHA(CPHA)
  ) u_slave (
    .sclk    (sclk),
    .rst_n   (rst_n),
    .cs_n    (cs_n),
    .mosi    (mosi),
    .tx_data (slave_tx_data),
    .miso    (miso),
    .rx_data (slave_rx_data)
  );

endmodule

OFF-chip Protocols/SPI/TB_spi.v
module tb_spi;

  // Testbench signals
  reg clk;
  reg rst_n;
  reg start;
  reg [7:0] master_tx_data;
  reg [7:0] slave_tx_data;

  wire [7:0] master_rx_data;
  wire [7:0] slave_rx_data;
  wire busy;

  // DUT instantiation (PORT NAMES MATCH EXACTLY)
  spi_top dut (
    .clk            (clk),
    .rst_n          (rst_n),
    .start          (start),
    .master_tx_data (master_tx_data),
    .slave_tx_data  (slave_tx_data),
    .master_rx_data (master_rx_data),
    .slave_rx_data  (slave_rx_data),
    .busy           (busy)
  );

  // Clock generation
  always #5 clk = ~clk;

  // --------------------------------
  // SPI transfer task
  // --------------------------------
  task spi_transfer;
    input [7:0] m_tx;
    input [7:0] s_tx;
    begin
      master_tx_data = m_tx;
      slave_tx_data  = s_tx;

      @(posedge clk);
      start = 1;

      @(posedge clk);
      start = 0;

      // Wait for SPI to finish
      wait (busy == 0);
      #1;

      $display("[%0t] MASTER_TX=%h SLAVE_TX=%h | MASTER_RX=%h SLAVE_RX=%h",
                $time, m_tx, s_tx, master_rx_data, slave_rx_data);

      // Check
      if (master_rx_data !== s_tx)
        $display("❌ MASTER FAIL");
      else
        $display("✅ MASTER OK");

      if (slave_rx_data !== m_tx)
        $display("❌ SLAVE FAIL");
      else
        $display("✅ SLAVE OK");

      $display("----------------------------------");
    end
  endtask

  // --------------------------------
  // Test sequence
  // --------------------------------
  initial begin
    $dumpfile("spi.vcd");
    $dumpvars(0, tb_spi);

    $monitor("time = %0t | clk = %b,rst_n = %b,start = %b,master_tx_data = %b,slave_tx_data = %b,master_rx_data = %b,slave_rx_data = %b",$time,clk,rst_n,start,master_tx_data,slave_tx_data,master_rx_data,slave_rx_data);

    clk = 0;
    rst_n = 0;
    start = 0;
    master_tx_data = 0;
    slave_tx_data  = 0;

    #20 rst_n = 1;

    spi_transfer(8'hA5, 8'h3C);
    spi_transfer(8'h55, 8'hAA);
    spi_transfer(8'hF0, 8'h0F);

    #50;
    $finish;
  end

endmodule

OFF-chip Protocols/SPI/spi.vcd
$date
	Sun May 17 11:04:49 2026
$end
$version
	Icarus Verilog
$end
$timescale
	1s
$end
$scope module tb_spi $end
$var wire 8 ! slave_rx_data [7:0] $end
$var wire 8 " master_rx_data [7:0] $end
$var wire 1 # busy $end
$var reg 1 $ clk $end
$var reg 8 % master_tx_data [7:0] $end
$var reg 1 & rst_n $end
$var reg 8 ' slave_tx_data [7:0] $end
$var reg 1 ( start $end
$scope module dut $end
$var wire 1 $ clk $end
$var wire 1 ) cs_n $end
$var wire 8 * master_tx_data [7:0] $end
$var wire 1 & rst_n $end
$var wire 8 + slave_tx_data [7:0] $end
$var wire 1 ( start $end
$var wire 8 , slave_rx_data [7:0] $end
$var wire 1 - sclk $end
$var wire 1 . mosi $end
$var wire 1 / miso $end
$var wire 8 0 master_rx_data [7:0] $end
$var wire 1 # busy $end
$var parameter 32 1 CPHA $end
$var parameter 32 2 CPOL $end
$scope module u_master $end
$var wire 1 $ clk $end
$var wire 1 & rst_n $end
$var wire 1 3 sample_edge $end
$var wire 1 4 shift_edge $end
$var wire 1 ( start $end
$var wire 8 5 tx_data [7:0] $end
$var wire 1 / miso $end
$var parameter 32 6 CPHA $end
$var parameter 32 7 CPOL $end
$var reg 3 8 bit_cnt [2:0] $end
$var reg 1 # busy $end
$var reg 1 9 done_pending $end
$var reg 1 . mosi $end
$var reg 8 : rx_data [7:0] $end
$var reg 8 ; rx_shift [7:0] $end
$var reg 1 - sclk $end
$var reg 8 < tx_shift [7:0] $end
$upscope $end
$scope module u_slave $end
$var wire 1 ) cs_n $end
$var wire 1 . mosi $end
$var wire 1 & rst_n $end
$var wire 1 = sample_edge $end
$var wire 1 - sclk $end
$var wire 1 > shift_edge $end
$var wire 8 ? tx_data [7:0] $end
$var parameter 32 @ CPHA $end
$var parameter 32 A CPOL $end
$var reg 3 B bit_cnt [2:0] $end
$var reg 1 / miso $end
$var reg 8 C rx_data [7:0] $end
$var reg 8 D rx_shift [7:0] $end
$var reg 8 E tx_shift [7:0] $end
$upscope $end
$upscope $end
$scope task spi_transfer $end
$var reg 8 F m_tx [7:0] $end
$var reg 8 G s_tx [7:0] $end
$upscope $end
$upscope $end
$enddefinitions $end
$comment Show the parameter values. $end
$dumpall
b0 A
b0 @
b0 7
b0 6
b0 2
b0 1
$end
#0
$dumpvars
bx G
bx F
b0 E
b0 D
b0 C
b0 B
b0 ?
1>
0=
bx <
bx ;
b0 :
09
bx 8
b0 5
14
03
b0 0
0/
x.
0-
b0 ,
b0 +
b0 *
1)
0(
b0 '
0&
b0 %
0$
0#
b0 "
b0 !
$end
#5
1$
#10
0$
#15
1$
#20
0$
b111100 '
b111100 +
b111100 ?
b10100101 %
b10100101 *
b10100101 5
b111100 G
b10100101 F
1&
#25
b111100 E
b111 B
0)
b0 ;
b10100101 <
b111 8
1#
1(
1$
#30
0$
#35
b110 B
b1 D
b1111000 E
0>
04
1.
1=
13
1-
0(
1$
#40
0$
#45
1>
14
b110 8
0=
03
0-
1$
#50
0$
#55
b101 B
b10 D
b11110000 E
0>
04
0.
1=
13
1-
1$
#60
0$
#65
1>
14
b101 8
0=
03
0-
1$
#70
0$
#75
b100 B
b101 D
b11100000 E
1/
0>
04
1.
1=
13
1-
1$
#80
0$
#85
1>
14
b100 8
b100000 ;
0=
03
0-
1$
#90
0$
#95
b11 B
b1010 D
b11000000 E
0>
04
0.
1=
13
1-
1$
#100
0$
#105
1>
14
b11 8
b110000 ;
0=
03
0-
1$
#110
0$
#115
b10 B
b10100 D
b10000000 E
0>
04
1=
13
1-
1$
#120
0$
#125
1>
14
b10 8
b111000 ;
0=
03
0-
1$
#130
0$
#135
b1 B
b101001 D
b0 E
0>
04
1.
1=
13
1-
1$
#140
0$
#145
1>
14
b1 8
b111100 ;
0=
03
0-
1$
#150
0$
#155
b0 B
b1010010 D
0/
0>
04
0.
1=
13
1-
1$
#160
0$
#165
1>
14
b0 8
0=
03
0-
1$
#170
0$
#175
b111 B
b10100101 D
0>
04
1.
1=
13
1-
1$
#180
0$
#185
1>
14
19
0=
03
0-
1$
#190
0$
#195
b10100101 !
b10100101 ,
b10100101 C
1)
09
0#
b111100 "
b111100 0
b111100 :
0=
03
0-
1$
#196
b10101010 '
b10101010 +
b10101010 ?
b1010101 %
b1010101 *
b1010101 5
b10101010 G
b1010101 F
#200
0$
#205
b0 D
b10101010 E
0)
b0 ;
b1010101 <
b111 8
1#
1(
1$
#210
0$
#215
b110 B
b1010100 E
1/
0>
04
0.
1=
13
1-
0(
1$
#220
0$
#225
1>
14
b110 8
b10000000 ;
0=
03
0-
1$
#230
0$
#235
b101 B
b1 D
b10101000 E
0/
0>
04
1.
1=
13
1-
1$
#240
0$
#245
1>
14
b101 8
0=
03
0-
1$
#250
0$
#255
b100 B
b10 D
b1010000 E
1/
0>
04
0.
1=
13
1-
1$
#260
0$
#265
1>
14
b100 8
b10100000 ;
0=
03
0-
1$
#270
0$
#275
b11 B
b101 D
b10100000 E
0/
0>
04
1.
1=
13
1-
1$
#280
0$
#285
1>
14
b11 8
0=
03
0-
1$
#290
0$
#295
b10 B
b1010 D
b1000000 E
1/
0>
04
0.
1=
13
1-
1$
#300
0$
#305
1>
14
b10 8
b10101000 ;
0=
03
0-
1$
#310
0$
#315
b1 B
b10101 D
b10000000 E
0/
0>
04
1.
1=
13
1-
1$
#320
0$
#325
1>
14
b1 8
0=
03
0-
1$
#330
0$
#335
b0 B
b101010 D
b0 E
1/
0>
04
0.
1=
13
1-
1$
#340
0$
#345
1>
14
b0 8
b10101010 ;
0=
03
0-
1$
#350
0$
#355
b111 B
b1010101 D
0/
0>
04
1.
1=
13
1-
1$
#360
0$
#365
1>
14
19
0=
03
0-
1$
#370
0$
#375
b1010101 !
b1010101 ,
b1010101 C
1)
09
0#
b10101010 "
b10101010 0
b10101010 :
0=
03
0-
1$
#376
b1111 '
b1111 +
b1111 ?
b11110000 %
b11110000 *
b11110000 5
b1111 G
b11110000 F
#380
0$
#385
b0 D
b1111 E
0)
b0 ;
b11110000 <
b111 8
1#
1(
1$
#390
0$
#395
b110 B
b1 D
b11110 E
0>
04
1=
13
1-
0(
1$
#400
0$
#405
1>
14
b110 8
0=
03
0-
1$
#410
0$
#415
b101 B
b11 D
b111100 E
0>
04
1=
13
1-
1$
#420
0$
#425
1>
14
b101 8
0=
03
0-
1$
#430
0$
#435
b100 B
b111 D
b1111000 E
0>
04
1=
13
1-
1$
#440
0$
#445
1>
14
b100 8
0=
03
0-
1$
#450
0$
#455
b11 B
b1111 D
b11110000 E
0>
04
1=
13
1-
1$
#460
0$
#465
1>
14
b11 8
0=
03
0-
1$
#470
0$
#475
b10 B
b11110 D
b11100000 E
1/
0>
04
0.
1=
13
1-
1$
#480
0$
#485
1>
14
b10 8
b1000 ;
0=
03
0-
1$
#490
0$
#495
b1 B
b111100 D
b11000000 E
0>
04
1=
13
1-
1$
#500
0$
#505
1>
14
b1 8
b1100 ;
0=
03
0-
1$
#510
0$
#515
b0 B
b1111000 D
b10000000 E
0>
04
1=
13
1-
1$
#520
0$
#525
1>
14
b0 8
b1110 ;
0=
03
0-
1$
#530
0$
#535
b111 B
b11110000 D
b0 E
0>
04
1=
13
1-
1$
#540
0$
#545
1>
14
19
b1111 ;
0=
03
0-
1$
#550
0$
#555
b11110000 !
b11110000 ,
b11110000 C
0/
1)
09
0#
b1111 "
b1111 0
b1111 :
0=
03
0-
1$
